pusher_push_notifications/__init__.py
pusher_push_notifications-2.0.2.dist-info/LICENSE
pusher_push_notifications-2.0.2.dist-info/METADATA
pusher_push_notifications-2.0.2.dist-info/WHEEL
pusher_push_notifications-2.0.2.dist-info/top_level.txt
pusher_push_notifications-2.0.2.dist-info/RECORD
