Metadata-Version: 2.1
Name: pusher_push_notifications
Version: 2.0.2
Summary: Pusher Push Notifications Python server SDK
Author: Pusher
Author-email: support@pusher.com
Classifier: Intended Audience :: Developers
Classifier: Programming Language :: Python
Classifier: Programming Language :: Python :: 2
Classifier: Programming Language :: Python :: 2.7
Classifier: Programming Language :: Python :: 3
Classifier: Programming Language :: Python :: 3.4
Classifier: Programming Language :: Python :: 3.5
Classifier: Programming Language :: Python :: 3.6
Classifier: Programming Language :: Python :: 3.7
Classifier: Programming Language :: Python :: Implementation :: CPython
Requires-Python: >=2.7, !=3.0.*, !=3.1.*, !=3.2.*, !=3.3.*
License-File: LICENSE
Requires-Dist: six<2,>1.4.0
Requires-Dist: requests<3,>2.5.0
Requires-Dist: pyjwt<3,>1.1.0
